source_gitlab/__init__.py
source_gitlab/components/partition_routers.py
source_gitlab/config_migrations.py
source_gitlab/manifest.yaml
source_gitlab/run.py
source_gitlab/schemas/branches.json
source_gitlab/schemas/commits.json
source_gitlab/schemas/deployments.json
source_gitlab/schemas/epic_issues.json
source_gitlab/schemas/epics.json
source_gitlab/schemas/group_issue_boards.json
source_gitlab/schemas/group_labels.json
source_gitlab/schemas/group_members.json
source_gitlab/schemas/group_milestones.json
source_gitlab/schemas/groups.json
source_gitlab/schemas/issues.json
source_gitlab/schemas/jobs.json
source_gitlab/schemas/merge_request_commits.json
source_gitlab/schemas/merge_requests.json
source_gitlab/schemas/pipelines.json
source_gitlab/schemas/pipelines_extended.json
source_gitlab/schemas/project_labels.json
source_gitlab/schemas/project_members.json
source_gitlab/schemas/project_milestones.json
source_gitlab/schemas/projects.json
source_gitlab/schemas/releases.json
source_gitlab/schemas/tags.json
source_gitlab/schemas/users.json
source_gitlab/source.py
source_gitlab/spec.json
source_gitlab/utils.py
airbyte_source_gitlab-4.3.7.dist-info/METADATA
airbyte_source_gitlab-4.3.7.dist-info/WHEEL
airbyte_source_gitlab-4.3.7.dist-info/entry_points.txt
airbyte_source_gitlab-4.3.7.dist-info/RECORD
