Metadata-Version: 2.3
Name: airbyte-source-gitlab
Version: 4.3.7
Summary: Source implementation for GitLab.
License: MIT
Author: Airbyte
Author-email: contact@airbyte.io
Requires-Python: >=3.10,<3.12
Classifier: License :: OSI Approved :: MIT License
Classifier: Programming Language :: Python :: 3
Classifier: Programming Language :: Python :: 3.10
Classifier: Programming Language :: Python :: 3.11
Requires-Dist: airbyte-cdk (>=4,<5)
Requires-Dist: vcrpy (==4.1.1)
Project-URL: Documentation, https://docs.airbyte.com/integrations/sources/gitlab
Project-URL: Homepage, https://airbyte.com
Project-URL: Repository, https://github.com/airbytehq/airbyte
